CHANGES.md
subby/__init__.py
subby/core.py
subby/utils.py
subby-0.2.0.dist-info/LICENSE
subby-0.2.0.dist-info/WHEEL
subby-0.2.0.dist-info/METADATA
subby-0.2.0.dist-info/RECORD
