Metadata-Version: 2.1
Name: subby
Version: 0.2.0
Summary: Subprocesses simplified
Home-page: https://github.com/jdidion/subby
License: Apache-2.0
Author: John Didion
Author-email: github@didion.net
Requires-Python: >=3.6,<4.0
Classifier: Development Status :: 4 - Beta
Classifier: License :: OSI Approved :: Apache Software License
Classifier: Programming Language :: Python :: 3
Classifier: Programming Language :: Python :: 3.10
Classifier: Programming Language :: Python :: 3.6
Classifier: Programming Language :: Python :: 3.7
Classifier: Programming Language :: Python :: 3.8
Classifier: Programming Language :: Python :: 3.9
Project-URL: Repository, https://github.com/jdidion/subby.git
